py_alf/__init__.py
py_alf/alf_source.py
py_alf/ana.py
py_alf/analysis.py
py_alf/check_common.py
py_alf/check_rebin_ipy.py
py_alf/check_rebin_tk.py
py_alf/check_warmup_ipy.py
py_alf/check_warmup_tk.py
py_alf/exceptions.py
py_alf/init_layout.py
py_alf/lattice.py
py_alf/lattices_armv8.4-a.so
py_alf/lattices_x86-64.so
py_alf/simulation.py
py_alf/utils.py
py_alf/cli/__init__.py
py_alf/cli/alf_bin_count.py
py_alf/cli/alf_del_bins.py
py_alf/cli/alf_postprocess.py
py_alf/cli/alf_run.py
py_alf/cli/alf_show_obs.py
py_alf/cli/alf_test_branch.py
py_alf/cli/minimal_ALF_run.py
pyalf-2.6.post2.dist-info/licenses/LICENSE
pyalf-2.6.post2.dist-info/METADATA
pyalf-2.6.post2.dist-info/WHEEL
pyalf-2.6.post2.dist-info/entry_points.txt
pyalf-2.6.post2.dist-info/top_level.txt
pyalf-2.6.post2.dist-info/RECORD
