Metadata-Version: 2.4
Name: pyALF
Version: 2.6.post2
Summary: Python interface for ALF, plus scripts and Jupyter notebooks.
Author-email: ALF Collaboration <alf@physik.uni-wuerzburg.de>, Jonas Schwab <jonas.schwab@uni-wuerzburg.de>
License:                     GNU GENERAL PUBLIC LICENSE
Project-URL: Documentation, https://gitpages.physik.uni-wuerzburg.de/ALF/pyALF
Project-URL: Repository, https://git.physik.uni-wuerzburg.de/ALF/pyALF
Project-URL: Issues, https://git.physik.uni-wuerzburg.de/ALF/pyALF/-/issues
Project-URL: ALF Homepage, https://alf.physik.uni-wuerzburg.de/
Classifier: Programming Language :: Python :: 3
Classifier: License :: OSI Approved :: GNU General Public License v2 or later (GPLv2+)
Classifier: Operating System :: OS Independent
Requires-Python: >=3.7
License-File: LICENSE
Requires-Dist: f90nml
Requires-Dist: h5py
Requires-Dist: ipympl
Requires-Dist: ipywidgets
Requires-Dist: matplotlib
Requires-Dist: numba
Requires-Dist: numpy
Requires-Dist: pandas
Requires-Dist: scipy
Provides-Extra: gui
Requires-Dist: tkinter; extra == "gui"
Dynamic: license-file
